MANIFEST.in
README.rst
setup.py
alltweets/api.py
alltweets/constants.py
alltweets/crawler.py
alltweets/oauth.py
alltweets/parser.py
alltweets.egg-info/PKG-INFO
alltweets.egg-info/SOURCES.txt
alltweets.egg-info/dependency_links.txt
alltweets.egg-info/not-zip-safe
alltweets.egg-info/requires.txt
alltweets.egg-info/top_level.txt