Metadata-Version: 1.1
Name: alltweets
Version: 0.2
Summary: A very simple Twitter crawler that can collect all friends, followers, and tweets of a specified user.
Home-page: http://github.com/j1wan/alltweets
Author: Jiwan Jeong
Author-email: jiwanjeong@gmail.com
License: MIT
Keywords: Twitter crawl timeline
Platform: UNKNOWN
Classifier: Development Status :: 3 - Alpha
